<?xml version="1.0" encoding="UTF-8"?>
<msgs>  <modifiers/>    <msg index="1530"> <subject> <line> <f n="Aircraft_Type"><D2/></f>飞机的飞行距离和飞行高度属性。</line> </subject> <main> <line>&lt;p class=&apos;title&apos;&gt;<f n="Aircraft_Type"><D2/></f> (编号<D2/>)飞机属性&lt;/p&gt;<br/><br/></line>  <sub n="1"> <line>  以经济飞行高度飞行时的最大航程:<f n="UOM_AMT"><d>DISTANCE</d><S1.D1/></f><f n="UOM"><d>DISTANCE</d></f><br/></line> </sub> <sub n="2"> <line>  最大航行距离:<f n="UOM_AMT"><d>DISTANCE</d><S2.D1/></f> <f n="UOM"><d>DISTANCE</d></f><br/></line> </sub> <sub n="3"> <line>  以最大飞行高度飞行时的最大航程:<f n="UOM_AMT"><d>DISTANCE</d><S3.D1/></f> <f n="UOM"><d>DISTANCE</d></f><br/></line> </sub> <sub n="4"> <line>  满载燃油量: <f n="UOM_AMT"><d>WET_WEIGHT</d><S4.D1/></f> <f n="UOM"><d>WET_WEIGHT</d></f><br/></line> </sub> <sub n="5"> <line>  备用燃油的航行距离:<f n="UOM_AMT"><d>DISTANCE</d><S5.D1/></f> <f n="UOM"><d>DISTANCE</d></f><br/></line> </sub> <sub n="6"> <line>  空中交战时燃油附加消耗因子:<S6.D1/><br/></line> </sub> <sub n="7"> <line>  默认的飞机挂载:<S7.D1/><br/></line>  <sub n="1"> <line>  飞机挂载<S7.S1.D1/>的清单如下:<br/></line>  <sub n="1"> <line>  包括下列武器:<br/></line>  <sub n="1">  <group n="1"> <line>  <f j="left" n="Targetable_Weapon" p="15" w="15"><S7.S1.S1.S1.G1.D1/></f>   <S7.S1.S1.S1.G1.D2/><br/></line> </group></sub> <sub n="2"> <line>  无<br/></line> </sub></sub> <sub n="2"> <line>  包括下列传感器:<br/></line>  <sub n="1">  <group n="1"> <line>  <f n="Sensor_Type"><S7.S1.S2.S1.G1.D1/></f><br/></line> </group></sub> <sub n="2"> <line>  无<br/></line> </sub></sub> <sub n="3"> <line>  包括下列干扰机:<br/></line>  <sub n="1">  <group n="1"> <line>  <f n="Jammer_Type"><S7.S1.S3.S1.G1.D1/></f><br/></line> </group></sub> <sub n="2"> <line>  无<br/></line> </sub></sub> <sub n="4"> <line>  包括下列补给物资:<br/></line>  <sub n="1">  <group n="1"> <line>  补给类 <S7.S1.S4.S1.G1.D1 p="3" w="3"/>  <f j="left" n="Supply_Category" p="15" w="15"><S7.S1.S4.S1.G1.D1/></f>  <f n="SLP_SC_AMT" p="14" w="14"><d>0</d><S7.S1.S4.S1.G1.D1/><S7.S1.S4.S1.G1.D2/></f> <f n="SLP_SC_UOM"><d>0</d><S7.S1.S4.S1.G1.D1/></f><br/></line> </group></sub> <sub n="2"> <line>  无<br/></line> </sub></sub> <sub n="6"> <line>  包括以下数量的附加油料:<br/><br/></line> <line>  <f n="UOM_AMT"><d>WET_WEIGHT</d><S7.S1.S6.D1/></f> <f n="UOM"><d>WET_WEIGHT</d></f><br/></line> </sub></sub></sub> <sub n="8"> <line>  余油量:<f n="OUM_AMT"><d>DISTANCE</d><S8.D1/></f> <f n="UOM"><d>DISTANCE</d></f><br/></line> </sub> <sub n="9"> <line>  最大油量:<f n="UOM_AMT"><d>DISTANCE</d><S9.D1/></f> <f n="UOM"><d>DISTANCE</d></f><br/></line> </sub></main> </msg> </msgs>