<?xml version="1.0" encoding="UTF-8"?>
<msgs>  <modifiers/>    <msg index="2261"> <subject> <line>反炮兵行动情况报告</line> </subject> <main> <line>&lt;p class=&apos;title&apos;&gt;反炮兵行动情况报告&lt;/p&gt;</line>  <group n="1"> <line><br/>——<G1.D1/>雷达：</line>  <sub n="1"> <line>没有可执行反炮兵任务的部队。</line> </sub> <sub n="2"> <line>可指派以下部队执行反炮兵任务：</line> <line>&lt;p class=&apos;table_name&apos;&gt;可执行反炮兵任务部队列表&lt;/p&gt;</line> <line>__start_table |部队名称|弹药|数量（枚）|反击最小发射数（枚）|发现后最迟反击时间<br/></line>  <group n="1"> <line>|<f n="unit_name_transform"><G1.S2.G1.D1/></f></line> <line>|<f n="Targetable_Weapon"><G1.S2.G1.D3/></f>|<G1.S2.G1.D2/></line> <line>|<G1.S2.G1.D4/>|<f n="DURATION"><G1.S2.G1.D5/><d>%.2Tm</d></f>分钟<br/></line> </group><line>__stop_table</line> </sub> <sub n="3"> <line>当前不能参与作战，</line>  <sub n="1"> <line>预计恢复时间：<f n="GTIME"><G1.S3.S1.D1/></f>。</line> </sub> <sub n="2"> <line>因为雷达未按计划修复。</line> </sub></sub></group></main> </msg> </msgs>