<?xml version="1.0" encoding="UTF-8"?>
<msgs>  <modifiers/>    <msg index="3170"> <subject> <line>空中<D2/>编队任务调整情况报告</line> </subject> <main> <line>&lt;p class=&apos;title&apos;&gt;空中<D2/>编队任务调整情况报告&lt;/p&gt;</line> <line><br/>按照改变空中<D2/>编队任务参数的命令（批号：<D3/>），执行情况如下：</line>  <sub n="1"> <line><br/>加油任务选项未变，该空中编队不是加油机。</line> </sub> <sub n="2"> <line><br/>加油任务选项未变，该空中编队正在返航，参数无法变更。</line> </sub> <sub n="3"> <line><br/>加油任务选项未变，编队飞机已被击落，无法变更参数。</line> </sub> <sub n="4"> <line><br/>加油任务选项未变，该空中编队处在转场状态，无法变更参数。</line> </sub> <sub n="5"> <line><br/>加油任务选项已改变。今后可以为友方加油。</line> </sub> <sub n="6"> <line><br/>加油任务选项已改变。今后不能为友方加油。</line> </sub> <sub n="7">  <sub n="1"> <line><br/>空中编队命令ID已调整为“<S7.S1.D1/>”。</line> </sub> <sub n="2"> <line><br/>因空中编队命令ID“<S7.S2.D1/>”不存在，无法变更。</line> </sub> <sub n="3"> <line><br/>变更序号同样无法执行。</line> </sub> <sub n="4"> <line><br/>由于不能变更空中编队命令序号“<S7.S4.D1/>”，</line> <line>空中编队命令<S7.S4.D2/>尚未变更。</line> </sub> <sub n="5"> <line><br/>该任务不属于空中命令，无法将序号改为“<S7.S5.D1/>”。</line> </sub> <sub n="6"> <line><br/>该编队任务序号已由“<S7.S6.D2/>”变更为“<S7.S6.D1/>”。</line> </sub></sub> <sub n="8"> <line><br/>由于该空中编队没有担负防御任务，不能执行拦截行动，</line> <line>因此人工分配拦截目标的选项无法变更。</line> </sub> <sub n="9"> <line><br/>由于该空中编队正在返航，</line> <line>因此人工分配拦截目标的选项已无法变更。</line> </sub> <sub n="10"> <line><br/>由于该空中编队被摧毁，</line> <line>因此人工分配拦截目标的选项已无法变更。</line> </sub> <sub n="11"> <line><br/>由于该空中编队已转场，</line> <line>因此人工分配拦截目标的选项无法变更。</line> </sub> <sub n="12"> <line><br/>由于该空中编队正在执行区域防护或编队掩护任务，</line> <line>人工分配拦截目标的选项不能变更。</line> </sub> <sub n="13"> <line><br/>该空中编队的人工分配拦截目标选项变更，</line> <line>已不能自动执行拦截任务。</line> </sub> <sub n="14"> <line><br/>该空中编队的人工分配拦截目标选项已变更，</line> <line>可以自动执行拦截任务。</line> </sub> <sub n="15">  <sub n="1"> <line><br/>解除警戒时间已按要求改变，该空中编队将在<f n="GTIME"><S15.D1/></f>解除警戒。</line> </sub> <sub n="2"> <line><br/>脱离阵位时间已按要求改变，该空中编队将在<f n="GTIME"><S15.D1/></f>离开阵位。</line> </sub> <sub n="3"> <line><br/>该空中编队属于某空中机群，无法变更结束时间参数，</line> <line>因此脱离阵位时间不能改变。</line> </sub> <sub n="10"> <line><br/>该空中编队不能脱离阵位，</line> <line>因此脱离阵位时间无法改变。</line> </sub> <sub n="11"> <line><br/>该空中编队正在警戒，</line> <line>且没有结束警戒计划，</line> <line>因此结束警戒时间无法变更。</line> </sub> <sub n="12"> <line><br/>按照新的命令，该空中编队在结束警戒时间</line> <line>前尚未到达计划阵位，</line> <line>因此脱离阵位时间无法改变。</line> </sub> <sub n="13"> <line><br/>该空中编队航线无法确定，解除警戒或脱离阵位时间不能变更。</line> </sub> <sub n="14"> <line><br/>按照新的命令，该空中编队在脱离阵位时间</line> <line>前尚未抵达指定位置，</line> <line>因此脱离阵位时间无法改变。</line> </sub> <sub n="15"> <line><br/>按照新的命令，机组人员工作时间将超出上限，</line> <line>因此脱离阵位时间无法改变。</line> </sub></sub> <sub n="16"> <line><br/>该空中运输编队已返航，无法对其任务参数做出调整。</line> </sub> <sub n="17"> <line><br/>该空中运输编队装卸点之间航线已按命令做出调整。</line> </sub> <sub n="18"> <line><br/>该空中编队将按<f n="Lift_Land_Type"><S18.D1/></f>方式投送部队。</line> </sub> <sub n="19"> <line><br/>该空中编队已展开装载，因此已不能调整空运部队。</line> </sub> <sub n="20"> <line><br/>该空中编队已将部分部队运输至目的地，因此已不能调整空运部队。</line> </sub> <sub n="21"> <line><br/>该空中编队当前突遇<f n="Air_Mission_Posture"><S21.D1/></f>状态，</line> <line>因此不能调整空运部队。</line> </sub> <sub n="22"> <line><br/>该空中编队是空运该部队的唯一编队，</line> <line>这种情况下正在实施的空运任务不能中止，</line> <line>因此不能调整空运部队。</line> </sub> <sub n="23"> <line><br/>该空中编队已卸载部分空运部队，</line> <line>因此不能变更空运部队。</line> </sub> <sub n="24"> <line><br/>该空中编队由空运<f n="unit_name_transform"><S24.D1/></f></line> <line>调整为空运<f n="unit_name_transform"><S24.D2/></f>。</line> </sub> <sub n="25"> <line><br/>由于该空中编队正在等待装载，因此装载地域无法变更。</line> </sub> <sub n="26"> <line><br/>该空中编队装载地域已调整为<f n="LOCATION"><S26.D1/><S26.D2/></f>，</line> <line>将在装载点等待部队到达。</line> </sub> <sub n="27">  <sub n="1"> <line><br/>由于该空中编队不是沿航线巡逻，因此巡逻点未变更。</line> </sub> <sub n="2"> <line><br/>由于该空中编队正在返航且没有沿航线巡逻计划，因此巡逻点未变更。</line> </sub> <sub n="3"> <line><br/>由于该空中编队的引导编队<S27.S3.D1/></line> <line>尚未组建完成，因此巡逻点未变更。</line> </sub> <sub n="4"> <line><br/>由于该空中编队的引导编队<S27.S4.D1/>中没有舰艇</line> <line>与该编队隶属同一方，因此巡逻点未变更。</line> </sub> <sub n="5"> <line><br/>由于该空中编队的引导舰艇<f n="unit_name_transform"><S27.S5.D1/></f></line> <line>尚未进入演习区，因此巡逻点未变更。</line> </sub> <sub n="6"> <line><br/>由于该空中编队的引导实体<f n="unit_name_transform"><S27.S6.D1/></f></line> <line>已不存在，因此巡逻点未变更。</line> </sub> <sub n="7"> <line><br/>由于该空中编队不能在规定的脱离阵位时间前到达新的巡逻点，</line> <line>因此巡逻点未变更。</line> </sub> <sub n="8"> <line><br/>由于该空中编队在当前位置与新的巡逻点之间没有可通行航线，</line> <line>因此巡逻点未变更。</line> </sub> <sub n="9"> <line><br/>由于该空中编队尚未进入演习区，</line> <line>因此巡逻点未变更。</line> </sub> <sub n="10"> <line><br/>由于为该空中编队指定的作战区不存在，</line> <line>因此巡逻点未变更。</line> </sub> <sub n="11"> <line><br/>由于没有指定作战区域的具体信息，因此巡逻点未变更。</line> </sub> <sub n="12"> <line><br/>由于在指定作战区未发现水域，因此巡逻点未变更。</line> </sub> <sub n="13"> <line><br/>由于该空中编队已编入空中机群，因此巡逻点未变更。</line> </sub> <sub n="14"> <line><br/>由于该空中编队没有挂载巡逻所需的武器，因此巡逻点未变更。</line> </sub> <sub n="15"> <line><br/>由于该空中编队没有足够燃油，因此巡逻点未变更。</line> </sub> <sub n="16"> <line><br/>由于该空中编队没有引导舰艇或编队，因此巡逻点未变更。</line> </sub> <sub n="50"> <line><br/>巡逻点尚未按要求变更，该空中编队起飞后，将飞向新巡逻点。</line> </sub> <sub n="51"> <line><br/>巡逻点已按要求变更，该空中编队起飞后，将飞向新巡逻点。</line> </sub> <sub n="52"> <line><br/>巡逻点已按要求变更，该空中编队完成拦截或加油任务后，</line> <line>将调整航线飞向新巡逻点。</line> </sub> <sub n="53"> <line><br/>巡逻点已按要求变更，该空中编队将调整航线飞向新巡逻点。</line> </sub> <sub n="54"> <line><br/>巡逻点已按要求变更，该空中编队已离开当前巡逻点，</line> <line>正调整航线飞向新巡逻点。</line> </sub> <sub n="55"> <line><br/>已经为在机场的值班编队指定巡逻点，</line> <line>该编队起飞后将调整航线前往新巡逻点。</line> </sub> <sub n="56"> <line><br/>已经为在临时起降场的值班编队指定巡逻点，</line> <line>该编队起飞后将调整航线前往新巡逻点。</line> </sub></sub> <sub n="28"> <line><br/>由于该空中编队已装载完毕或正在装载过程中，</line> <line>改变空中编队装载点的命令无法执行。</line> </sub> <sub n="29"> <line><br/>由于该空中编队突遭变故处于<f n="Air_Mission_Posture"><S29.D1/></f>状态，</line> <line>改变空中编队装载点的命令无法执行。</line> </sub> <sub n="30"> <line><br/>由于该空中编队已装载部分部队，</line> <line>改变空中编队装载点的命令无法执行。</line> </sub> <sub n="31"> <line><br/>该空中编队已按命令将装载点变更为</line> <line><f n="LOCATION"><S31.D1/><S31.D2/></f>，现正调整航线。</line> </sub> <sub n="32"> <line><br/>由于该空中编队是空运该部队的唯一编队，且正在实施过程中，</line> <line>变更装载点的命令无法执行。</line> </sub> <sub n="33"> <line><br/>该空中编队已按命令将卸载点变更为</line> <line><f n="LOCATION"><S33.D1/><S33.D2/></f>，当前该编队尚未装载部队。</line> </sub> <sub n="34"> <line><br/>由于该空中编队正在原卸载点实施卸载，</line> <line>变更卸载点的命令已无法执行。</line> </sub> <sub n="35"> <line><br/>由于该空中编队已在其他地域卸载了部分部队，</line> <line>变更卸载点的命令已无法执行。</line> </sub> <sub n="36"> <line><br/>该空中编队最后一批搭载部队已登机，</line> <line>现位于其他卸载点，</line> <line>变更卸载点的命令已无法执行。</line> </sub> <sub n="37"> <line><br/>该空中编队已按命令将卸载点变更为<f n="LOCATION"><S37.D1/><S37.D2/></f>，</line> <line>现部队已开始装载。</line> </sub> <sub n="38">  <group n="1">  <sub n="1"> <line><br/>—调整运输项<S38.G1.D1/>，拒绝，无此项。</line> </sub> <sub n="2"> <line><br/>—调整运输项<S38.G1.D1/>，拒绝，编队已经实施。</line> </sub> <sub n="3"> <line><br/>—调整运输项<S38.G1.D1/>，拒绝，未指定补给列表。</line> </sub> <sub n="4"> <line><br/>—调整运输项<S38.G1.D1/>，执行：</line> <line><br/>——位置：<f n="LOCATION"><S38.G1.D2/><S38.G1.D3/></f>；</line> <line><br/>——接收方：<S38.G1.D4/>；</line> <line><br/>——离开时间：<f n="GTIME"><S38.G1.D6/></f>；</line> <line><br/>——运输类型：<f n="All_Transport_Types"><S38.G1.D5/></f>；</line> <line><br/>——高度：<f n="UOM_AMT"><d>AIRDISTANCE</d><S38.G1.D7/></f><f n="UOM"><d>AIRDISTANCE</d></f>；</line>  <group n="1"> <line><br/>——<f n="SLP_Category_Name"><S38.G1.D8/><S38.G1.S4.G1.D1/></f>：<f n="SLP_SC_AMT"><S38.G1.D8/><S38.G1.S4.G1.D1/><S38.G1.S4.G1.D2/></f><f n="SLP_SC_UOM"><S38.G1.D8/><S38.G1.S4.G1.D1/></f></line> </group></sub> <sub n="5"> <line><br/>—删除运输项<S38.G1.D1/>，拒绝，编队已经实施。</line> </sub> <sub n="6"> <line><br/>—删除运输项<S38.G1.D1/>，执行。</line> </sub> <sub n="7"> <line><br/>—在运输项<S38.G1.D1/>之后添加项<S38.G1.D2/>，执行。</line> </sub> <sub n="8"> <line><br/>—删除运输项<S38.G1.D1/>，拒绝，无此项。</line> </sub> <sub n="9"> <line><br/>—在运输项<S38.G1.D1/>之后添加项，拒绝，无此项。</line> </sub></group></sub> <sub n="39">  <group n="1">  <sub n="1"> <line><br/>—调整运输项<S39.G1.D1/>，拒绝，无此项。</line> </sub> <sub n="2"> <line><br/>—调整运输项<S39.G1.D1/>，拒绝，编队已经实施。</line> </sub> <sub n="3"> <line><br/>—调整运输项<S39.G1.D1/>，拒绝，未经允许的输送点或特种部队。</line> </sub> <sub n="4"> <line><br/>—调整运输项<S39.G1.D1/>，拒绝，未指定特种部队。</line> </sub> <sub n="5"> <line><br/>—调整运输项<S39.G1.D1/>，拒绝，以下特种部队未识别：</line>  <group n="1"> <line><br/>——<f n="unit_name_transform"><S39.G1.S5.G1.D1/></f></line> </group></sub> <sub n="6"> <line><br/>—删除运输项<S39.G1.D1/>，拒绝，编队已经实施。</line> </sub> <sub n="7"> <line><br/>—删除运输项<S39.G1.D1/>，拒绝，无此项。</line> </sub> <sub n="8"> <line><br/>—在运输项<S39.G1.D1/>之后添加项，拒绝，无此项。</line> </sub></group> <sub n="1"> <line><br/>—命令不能执行，<f n="unit_name_transform"><S39.S1.D1/></f>已在飞机上，不能装载。</line> </sub> <sub n="2"> <line><br/>—命令不能执行，<f n="unit_name_transform"><S39.S2.D1/></f>不在飞机上，不能空投。</line> </sub> <sub n="3"> <line><br/>—命令不能执行，<S39.S3.D1/>为未知程序。</line> </sub> <sub n="4"> <line><br/>—命令接受，正在返航。</line> </sub> <sub n="5"> <line><br/>—命令接受，任务继续。</line> </sub> <sub n="6"> <line><br/>—命令不能执行，变更不可行。</line> </sub></sub> <sub n="40">  <sub n="1"> <line><br/>该空中编队盘旋高度未变更，原因是无法确定空中编队当前状态。</line> </sub> <sub n="2"> <line><br/>该空中编队盘旋高度已变更，当前正在警戒，</line> <line>当指定位置后，将在指定高度盘旋。</line> </sub> <sub n="3"> <line><br/>该空中编队盘旋高度未变更，原因是当前</line> <line><br/>正前往盘旋中心点，到达后将在指定高度盘旋。</line> </sub> <sub n="4"> <line><br/>该空中编队盘旋高度已变更，当前正按指定高度盘旋。</line> </sub></sub> <sub n="41"> <line><br/>该空中编队掩护半径未变更，原因是没有执行空中防御任务。</line> </sub> <sub n="42"> <line><br/>该空中编队掩护半径已变更为<S42.D1/>海里</line> <line>（<f n="UOM_AMT"><d>DISTANCE</d><S42.D1/></f><f n="UOM"><d>DISTANCE</d></f>）。</line> </sub> <sub n="43">  <sub n="1"> <line><br/>该空中编队武器挂载未变更，因为现挂载能满足任务需求。</line> </sub> <sub n="2"> <line><br/>该空中编队武器挂载未变更，因为命令中的武器挂载</line> <line>包括对地突击弹药，而这是任务必需的。</line> </sub> <sub n="3"> <line><br/>该空中编队武器挂载未变更，因为命令中的武器挂载</line> <line>没有对地突击弹药，不符合任务需求。</line> </sub> <sub n="4"> <line><br/>命令中指定的武器挂载存在问题，</line> <line>该空中编队将从空中作战中心获取挂载信息。</line> </sub> <sub n="5"> <line><br/>该空中编队武器挂载已变更。</line> </sub></sub> <sub n="44">  <sub n="1"> <line><br/>命令要求的飞行速度<f n="UOM_AMT"><d>SPEED</d><S44.D1/></f><f n="UOM"><d>SPEED</d></f>，</line> <line>已低于该编队失速速度<f n="UOM_AMT"><d>SPEED</d><S44.D2/></f><f n="UOM"><d>SPEED</d></f>。</line> </sub> <sub n="2"> <line><br/>命令要求的飞行速度<f n="UOM_AMT"><d>SPEED</d><S44.D1/></f><f n="UOM"><d>SPEED</d></f>，</line> <line>已高于该编队最大速度<f n="UOM_AMT"><d>SPEED</d><S44.D2/></f><f n="UOM"><d>SPEED</d></f>。</line> </sub> <sub n="3"> <line><br/>要求该空中编队调整飞行速度的命令已执行，</line> <line>命令要求速度为<f n="UOM_AMT"><d>SPEED</d><S44.D1/></f><f n="UOM"><d>SPEED</d></f>，</line> <line>编队当前速度为<f n="UOM_AMT"><d>SPEED</d><S44.D2/></f><f n="UOM"><d>SPEED</d></f>。</line>  <sub n="1"> <line>编队尚未变速，是由于正在实施空中拦截，或属于某一机群。</line> </sub></sub></sub> <sub n="45">  <sub n="1"> <line><br/>该空中编队出航航线已变更。</line> </sub> <sub n="2"> <line><br/>该空中编队出航航线未变更，原因是该编队属于某一机群，并已抵达会合点。</line> </sub> <sub n="3"> <line><br/>该空中编队正在担负基地值班任务。除非指定</line> <line>新的巡逻点，否则调整出航航线没有意义。</line> </sub> <sub n="4"> <line><br/>该空中编队正在担负值班任务。除非指定</line> <line>新的巡逻点，否则调整出航航线没有意义。</line> </sub> <sub n="5"> <line><br/>该空中编队已过出航航线，新的出航航线命令取消。</line> </sub></sub> <sub n="46"> <line><br/>该空中编队武器挂载已变更，</line> <line>指定挂载武器如下：</line> <line>&lt;p class=&apos;table_name&apos;&gt;空中编队武器挂载清单&lt;/p&gt;</line> <line>__start_table|武器名称|数量<br/></line>  <group n="1"> <line>|<f n="Targetable_Weapon"><S46.G1.D1/></f>|<S46.G1.D2/><br/></line> </group><line>__stop_table</line> </sub> <sub n="47">  <sub n="1"> <line><br/>该空中编队返航航线已变更。</line> </sub> <sub n="2"> <line><br/>由于该空中编队没有航线或航线没有终点，因此不能添加返航航线。</line> </sub></sub> <sub n="48"> <line><br/>该空中巡逻编队现掩护作战区<S48.D1/>。</line> </sub> <sub n="49"> <line><br/>命令该空中巡逻编队掩护的作战区无效，命令取消。</line> </sub> <sub n="50">  <sub n="1"> <line><br/>该空中编队的敌我识别模式1未变更为<S50.S1.D1/>，</line> <line>飞机没有模式1敌我识别装备。</line> </sub> <sub n="2"> <line><br/>该空中编队的敌我识别模式1已变更为<S50.S2.D1/>，</line> </sub> <sub n="3"> <line><br/>该空中编队的敌我识别模式2未变更为<S50.S3.D1/>，</line> <line>飞机没有飞行中可变模式2敌我识别装备。</line> </sub> <sub n="4"> <line><br/>该空中编队的敌我识别模式2已变更为<S50.S4.D1/>，</line> </sub> <sub n="5"> <line><br/>该空中编队的敌我识别模式2未变更为<S50.S5.D1/>，</line> <line>飞机没有模式2敌我识别装备。</line> </sub> <sub n="6"> <line><br/>该空中编队的敌我识别模式3未变更为<S50.S6.D1/>，</line> <line>飞机没有模式3敌我识别装备。</line> </sub> <sub n="7"> <line><br/>该空中编队的敌我识别模式3已变更为<S50.S7.D1/>，</line> </sub> <sub n="8"> <line><br/>该空中编队的敌我识别模式1未变更为<S50.S8.D1/>，</line> <line>指定代码不是对敌我识别装备有效的二进制值。</line> </sub> <sub n="9"> <line><br/>该空中编队的敌我识别模式2未变更为<S50.S9.D1/>，</line> <line>指定代码不是对敌我识别装备有效的四进制值。</line> </sub> <sub n="10"> <line><br/>该空中编队的敌我识别模式3未变更为<S50.S10.D1/>，</line> <line>指定代码不是对敌我识别装备有效的四进制值。</line> </sub></sub> <sub n="51"> <line><br/>按命令，已将该空中编队是否进入敌防空区选项</line> <line>设置为“<f n="Ignore_Air_Defense"><S51.D1/></f>”。</line> </sub> <sub n="52"> <line><br/>该空中编队已受领战略空运计划。</line>  <sub n="1"> <line>当前编队飞行航线不能改变。</line> </sub> <sub n="2"> <line>为满足任务需要，编队已调整航线。</line> </sub> <sub n="3"> <line>为满足任务需要，编队在完成加油后将调整航线。</line> </sub> <sub n="4"> <line>以下计划航线点：</line>  <group n="1">  <sub n="1"> <line><br/>——<S52.S4.G1.S1.D1/>，拒绝，（ICAO）<S52.S4.G1.S1.D2/>不存在。</line> </sub> <sub n="2"> <line><br/>——<S52.S4.G1.S2.D1/>，拒绝，</line>  <sub n="1"> <line>与<S52.S4.G1.S2.S1.D2/>相关联的（ICAO）<S52.S4.G1.S2.S1.D1/>不在演习区。</line> </sub> <sub n="2"> <line><S52.S4.G1.S2.S2.D1/>不在演习区。</line> </sub></sub> <sub n="3"> <line><br/>——<S52.S4.G1.S3.D1/>，拒绝，指定地域（<f n="LOCATION"><S52.S4.G1.S3.D2/><S52.S4.G1.S3.D3/></f>）对于该舰艇深度不够。</line> </sub> <sub n="4"> <line><br/>——<S52.S4.G1.S4.D1/>，拒绝，计划已执行该站点序号<S52.S4.G1.S4.D2/>。</line> </sub> <sub n="5"> <line><br/>——<S52.S4.G1.S5.D1/>，接受。</line> </sub> <sub n="6"> <line><br/>——<S52.S4.G1.S6.D1/>，拒绝，该站点不存在。</line> </sub> <sub n="7"> <line><br/>——<S52.S4.G1.S7.D1/>，已从计划中删除。</line> </sub></group></sub></sub> <sub n="64"> <line><br/>空中加油计划变更如下：</line>  <group n="1">  <sub n="1"> <line><br/>由于加油机<S64.G1.S1.D1/>正在返航，其预留燃油量不能变更。</line> </sub> <sub n="2"> <line><br/>由于<S64.G1.S2.D2/>编队不存在，</line> <line>要求加油机<D2/>为该编队预留燃油量</line> <line>（<f n="UOM_AMT"><d>WET_WEIGHT</d><S64.G1.S2.D1/></f><f n="UOM"><d>WET_WEIGHT</d></f>）</line> <line>变更的命令无法执行。</line> </sub> <sub n="3"> <line><br/>由于<S64.G1.S3.D2/>编队与加油机<D2/>属同一编队，</line> <line>要求该加油机预留燃油量</line> <line>（<f n="UOM_AMT"><d>WET_WEIGHT</d><S64.G1.S3.D1/></f><f n="UOM"><d>WET_WEIGHT</d></f>）</line> <line>变更的命令无法执行。</line> </sub> <sub n="4"> <line><br/>加油机<D2/>为空中<S64.G1.S4.D2/>编队预留燃油量</line> <line>已增加<f n="UOM_AMT"><d>WET_WEIGHT</d><S64.G1.S4.D1/></f><f n="UOM"><d>WET_WEIGHT</d></f>。</line> </sub> <sub n="5"> <line><br/>加油机<D2/>已为空中<S64.G1.S5.D2/>编队</line> <line>预留燃油<f n="UOM_AMT"><d>WET_WEIGHT</d><S64.G1.S5.D1/></f><f n="UOM"><d>WET_WEIGHT</d></f>。</line> </sub> <sub n="6"> <line><br/>加油机<D2/>为空中<S64.G1.S6.D2/>编队预留燃油量</line> <line>已减少<f n="UOM_AMT"><d>WET_WEIGHT</d><S64.G1.S6.D1/></f><f n="UOM"><d>WET_WEIGHT</d></f>。</line> </sub> <sub n="7"> <line><br/>加油机<D2/>不再为空中<S64.G1.S7.D2/>编队预留油料，因为</line> <line>要求减少量（<f n="UOM_AMT"><d>WET_WEIGHT</d><S64.G1.S7.D1/></f><f n="UOM"><d>WET_WEIGHT</d></f>）</line> <line>超出了之前的预留量。</line> </sub> <sub n="8"> <line><br/>要求减少为空中<S64.G1.S8.D2/>编队预留燃油量</line> <line>（<f n="UOM_AMT"><d>WET_WEIGHT</d><S64.G1.S8.D1/></f><f n="UOM"><d>WET_WEIGHT</d></f>）的命令</line> <line>无效，加油机<D2/>没有为该空中编队预留油料。</line> </sub> <sub n="9"> <line><br/>要求为<S64.G1.S9.D2/>编队预留油量</line> <line>（<f n="UOM_AMT"><d>WET_WEIGHT</d><S64.G1.S9.D1/></f><f n="UOM"><d>WET_WEIGHT</d></f>）的命令</line> <line>无法执行，因为该编队没有空中加油能力。</line> </sub><line><br/></line> </group></sub> <sub n="65"> <line><br/>对情报搜索区调整情况：</line>  <group n="1"> <line><br/>——情报搜索区<S65.G1.D1/>，</line>  <sub n="1"> <line>已加入该编队情报搜索区列表。</line> </sub> <sub n="2"> <line>在该编队情报搜索区列表中已存在。</line> </sub> <sub n="3"> <line>已从该编队情报搜索区列表中删除。</line> </sub> <sub n="4"> <line>不在该编队情报搜索区列表中。</line> </sub> <sub n="5"> <line>当前不存在。</line> </sub> <sub n="6"> <line>该编队为空中游猎编队，不执行情报搜索区任务。</line> </sub></group></sub> <sub n="66"> <line><br/>已通知该空中编队，不允许自动攻击已发现目标。</line> </sub> <sub n="67"> <line><br/>已通知该空中编队，允许自动攻击已发现目标。</line> </sub> <sub n="68"> <line><br/>已通知该空中编队，不再允许自动攻击已发现目标。</line> </sub> <sub n="69"> <line><br/>已通知该空中编队，能够自动攻击已发现目标。</line> </sub> <sub n="70"> <line><br/>已通知该空中编队，不允许接受近距空中支援请求。</line> </sub> <sub n="71"> <line><br/>已通知该空中编队，可以接受近距空中支援请求，并已受领任务。</line> </sub> <sub n="72"> <line><br/>已通知该空中编队，可以接受近距空中支援请求，但当前没有任务。</line> </sub> <sub n="73"> <line><br/>已通知该空中编队，不再允许接受近距空中支援请求。当前</line> <line>该编队正在执行一项近距支援任务。</line> <line>如果要取消此任务，需下达取消空中任务命令。</line> </sub> <sub n="74"> <line><br/>已通知该空中编队，不再允许接受近距空中支援请求。</line> </sub> <sub n="75"> <line><br/>已通知该空中编队，可以接受近距空中支援请求</line> </sub> <sub n="76"> <line><br/>已通知该空中编队，将作为预备力量随时准备支援指定的作战部队。</line> </sub> <sub n="77"> <line><br/>该空中编队的被支援部队已变更，但</line> <line>现在该编队尚不允许执行近距空中支援任务，</line> <line>可另外下达调整空中任务参数命令，允许其接受近距空中支援请求。</line> </sub> <sub n="78"> <line><br/>该空中编队的被支援部队已变更，</line> <line>该编队正在对该部队所属单位实施近距空中支援。</line> </sub> <sub n="79"> <line><br/>该空中编队的被支援部队已变更，</line> <line>该编队正在对另外一支部队实施近距空中支援，</line> <line>如果需要停止该支援行动，可下达取消空中任务命令。</line> </sub> <sub n="80"> <line><br/>该空中编队的被支援部队已变更，</line> <line>并且，该编队已受领对新指定部队的近距空中支援请求。</line> </sub> <sub n="81"> <line><br/>该空中编队的被支援部队已变更，</line> <line>当前没有任务请求。</line> </sub> <sub n="85">  <sub n="1"> <line><br/>指定的空军收容部队<f n="unit_name_transform"><S85.D1/></f>不能使用，</line> <line>该部队适用航母，该空中编队飞机不能在航母起降，</line> <line>因此，变更降落点的命令无法执行。</line> </sub> <sub n="2"> <line><br/>指定的急降机场<f n="unit_name_transform"><S85.D1/></f>不能使用，</line> <line>该机场跑道长度不够，</line> <line>因此，变更降落点的命令无法执行。</line> </sub> <sub n="3"> <line><br/>指定的空军收容部队<f n="unit_name_transform"><S85.D1/></f>不能使用，</line> <line>该空中编队飞机是固定翼飞机，但无跑道可用，</line> <line>因此，变更降落点的命令无法执行。</line> </sub> <sub n="4"> <line><br/>不能在指定航母<f n="unit_name_transform"><S85.D1/></f>上迫降，</line> <line>该编队飞机不具备航母起降能力，</line> <line>因此，变更降落点的命令无法执行。</line> </sub> <sub n="5"> <line><br/>返航的飞行中队不能调整为基地警戒编队，</line> <line>因此，变更降落点至<f n="unit_name_transform"><S85.D1/></f>的命令无法执行。</line> </sub> <sub n="6"> <line><br/>当该飞机抵达指定编队位置时，将转场至<f n="unit_name_transform"><S85.D1/></f>。</line> </sub> <sub n="7"> <line><br/>起飞后，当该飞机抵达</line> <line>指定编队位置时，将转场至<f n="unit_name_transform"><S85.D1/></f>。</line> </sub> <sub n="8"> <line><br/>该飞机当前调整航线，转场至<f n="unit_name_transform"><S85.D1/></f>。</line> </sub> <sub n="9"> <line><br/>指定的空军收容部队<f n="unit_name_transform"><S85.D1/></f>不能使用，</line> <line>该空中编队与其机型不同，因此变更降落点的命令无法执行。</line> </sub> <sub n="10"> <line><br/>不能在指定航母<f n="unit_name_transform"><S85.D1/></f>上迫降，</line> <line>该编队飞机不具备航母起降能力，</line> <line>因此，变更降落点的命令无法执行。</line> </sub> <sub n="12"> <line><br/>不能在指定舰艇<f n="unit_name_transform"><S85.D1/></f>上迫降，</line> <line>该编队飞机为直升机，而该舰艇不能起降直升机，</line> <line>因此，变更降落点的命令无法执行。</line> </sub> <sub n="13"> <line><br/>不能在指定航母<f n="unit_name_transform"><S85.D1/></f>上迫降，</line> <line>当前航母上所有弹射装置不能正常使用，</line> <line>因此，变更降落点的命令无法执行。</line> </sub> <sub n="14"> <line><br/>不能在指定舰艇<f n="unit_name_transform"><S85.D1/></f>上迫降，</line> <line>该编队为固定翼飞机，只能在航母起降，</line> <line>因此，变更降落点的命令无法执行。</line> </sub></sub> <sub n="91"> <line><br/>需要掩护的空中编队列表已按命令调整。</line>  <sub n="1"> <line>但存在以下错误：</line>  <group n="1">  <sub n="1"> <line><br/>至少一个空中编队未被掩护。</line> </sub> <sub n="2"> <line><br/>至少一个指定的空中编队已被掩护。</line> </sub> <sub n="3"> <line><br/>至少一个指定的空中编队不再存在。</line> </sub></group><line><br/></line> </sub> <sub n="2"> <line>该空中编队没有被赋予任何掩护任务。</line> <line><br/></line> </sub> <sub n="3"> <line><br/>该空中编队负责掩护以下空中编队：</line>  <group n="1"> <line><br/>——<S91.S3.G1.D1/></line> </group></sub></sub> <sub n="92"> <line><br/>今后该空中编队如果被拦截，将不会撤离。</line> </sub> <sub n="93"> <line><br/>今后该空中编队如果被拦截，将可以撤离。</line> </sub> <sub n="94">  <sub n="1"> <line><br/>该空中编队已经展开雷达干扰行动。</line> </sub> <sub n="2"> <line><br/>该空中编队将展开雷达干扰行动。</line> </sub> <sub n="3"> <line><br/>该空中编队将对<f n="unit_name_transform"><S94.S3.D1/></f>展开多向通信干扰。</line> </sub> <sub n="4"> <line><br/>该空中编队将对<f n="unit_name_transform"><S94.S4.D1/></f></line> <line>及其所属部队实施通信干扰。</line> </sub> <sub n="5"> <line><br/>该空中编队将对<f n="No_Force_Side"><S94.S5.D1/></f>实施通信干扰。</line> </sub> <sub n="6"> <line><br/>按照命令，该空中编队要对</line> <line><f n="unit_name_transform"><S94.S6.D1/></f>实施心理战广播，</line> <line>但由于该集团不存在，命令无法执行。</line> </sub> <sub n="7"> <line><br/>该空中编队将对<f n="unit_name_transform"><S94.S7.D1/></f>实施心理战广播。</line> </sub> <sub n="8"> <line><br/>该空中编队将对<f n="unit_name_transform"><S94.S8.D1/></f></line> <line>及其所属部队实施心理战广播。</line> </sub> <sub n="9"> <line><br/>该空中编队挂载方案已确定，</line> <line>但由于没有所需的<f n="Jammer_Function"><S94.D1/></f>设备，干扰任务无法完成。</line> </sub> <sub n="10"> <line><br/>该空中编队挂载方案中没有<f n="Jammer_Function"><S94.D1/></f>设备，</line> <line>调整命令无法执行。</line> </sub> <sub n="11"> <line><br/>该空中编队受命实施<f n="Jammer_Function"><S94.D1/></f>行动，</line> <line>但由于未指定干扰部队或集团，</line> <line>该命令无法执行。</line> </sub> <sub n="13"> <line><br/>当进行干扰设备调整时，产生错误分配信息。</line> </sub></sub> <sub n="95">  <sub n="1"> <line><br/>警戒位置没有调整，</line> <line>担任舰艇警戒任务的固定翼飞行中队必须属海军序列，同时舰艇必须是航母。</line> </sub> <sub n="2"> <line><br/>警戒位置没有调整，</line> <line>直升机中队只能以直升机母舰为警戒点。</line> </sub> <sub n="3"> <line><br/>警戒位置没有调整，</line> <line>编队不能为作战区外的部队实施警戒。</line> </sub> <sub n="4"> <line><br/>警戒位置没有调整，该编队不具备警戒能力。</line> </sub> <sub n="7"> <line><br/>警戒位置没有调整，</line> <line>该编队不可能在规定时间到达新警戒位置。</line> </sub> <sub n="8"> <line><br/>警戒位置没有调整，该编队已达执行任务上限。</line> </sub> <sub n="10"> <line><br/>警戒位置没有调整，指定的基地或起降场不存在。</line> </sub> <sub n="13"> <line><br/>警戒位置没有调整，该编队属某空中机群。</line> </sub> <sub n="51"> <line><br/>警戒位置已按命令调整，</line> <line>该编队将在新位置实施警戒。</line> </sub> <sub n="52"> <line><br/>警戒位置已按命令调整，</line> <line>该编队将飞到新位置实施警戒。</line> </sub> <sub n="53"> <line><br/>警戒位置已按命令调整，</line> <line>该编队将在补充燃料和物资后转至新警戒位置。</line> </sub> <sub n="54"> <line><br/>该编队在返航时受领警戒任务，</line> <line>将在机场或附近执行新的警戒任务。</line> </sub> <sub n="55"> <line><br/>该编队在飞往原定警戒点时受领新的警戒任务，</line> <line>将调整航线至新的警戒位置。</line> </sub> <sub n="56"> <line><br/>该编队在飞往任务终点时受领新的警戒任务，</line> <line>在完成当前任务后将飞往新的警戒位置。</line> </sub> <sub n="57"> <line><br/>警戒位置已按命令调整，</line> <line>该编队在完成拦截任务后将飞往新警戒位置。</line> </sub> <sub n="58"> <line><br/>警戒位置没有调整，该编队不是警戒编队。</line> </sub> <sub n="59"> <line><br/>警戒位置没有调整，该编队油料不足，无法执行警戒任务。</line> </sub> <sub n="60"> <line><br/>该编队在返航时受领警戒任务，</line> <line>将调整航线至新的警戒位置。</line> </sub> <sub n="61"> <line><br/>警戒位置已按命令调整，</line> <line>在加油后将飞往新的警戒位置。</line> </sub> <sub n="62"> <line><br/>该编队在飞往任务终点时受领新的警戒任务，</line> <line>在完成攻击任务后将飞往新的警戒位置。</line> </sub> <sub n="77"> <line><br/>警戒位置没有调整，该编队当前状态不能受领新的警戒任务。</line> </sub></sub> <sub n="96"> <line><br/>编队呼号已经调整为“<S96.D1/>”。</line> </sub> <sub n="97">  <sub n="1"> <line><br/>如果没有空中走廊，编队航线将重新设定。</line> </sub> <sub n="2"> <line><br/>编队航线将重新设定或使用可用的空中走廊。</line> </sub></sub> <sub n="98"> <line><br/>该编队的目标类型优先级列表已经调整，</line> <line>将主要寻找下列目标类型：</line>  <group n="1"> <line><br/>——<f n="Target_Type_Group"><S98.G1.D1/></f></line> </group></sub> <sub n="99">  <sub n="2"> <line><br/>该编队目标类型优先级列表没有调整，</line> <line>指定的目标类型不适合该编队。</line> </sub></sub></main> </msg> </msgs>