<?xml version="1.0" encoding="UTF-8"?>
<msgs>  <modifiers/>    <msg index="4510"> <subject> <line><f n="unit_name_transform"><D2/></f>（运输队）遭敌攻击情况报告</line> </subject> <main> <line>&lt;p class=&apos;title&apos;&gt;<f n="unit_name_transform"><D2/></f>（运输队）遭敌攻击情况报告&lt;/p&gt;</line> <line><br/><f n="unit_name_transform"><D2/></f>向<f n="unit_name_transform"><D6/></f>报告：</line>  <sub n="1"> <line><f n="unit_name_transform"><S1.D1/></f>正在执行<f n="Supply_Shipment_Method"><S1.D2/></f>运输，</line> <line>于<f n="GTIME"><D1/></f>，在<f n="LOCATION"><D3/><D4/></f>地域，遭敌攻击。</line>  <sub n="1"> <line>正在执行运输<f n="unit_name_transform"><S1.S1.D1/></f>的任务，</line> <line>当前<f n="Transport_Convoy_Status"><S1.S1.D2/></f>。</line> </sub> <sub n="2"> <line>当前状态：<f n="Convoy_Status"><S1.S2.D1/></f>。</line> </sub></sub> <sub n="6"> <line>主要遭受地面火力突击。</line> </sub> <sub n="7"> <line>主要遭受炮兵火力突击。</line> </sub> <sub n="8"> <line>主要遭受空中火力突击。</line> </sub> <sub n="9"> <line>主要遭受导弹火力突击。</line> </sub> <sub n="10"> <line>&lt;p class=&apos;table_name&apos;&gt;该运输分队运输工具现状&lt;/p&gt;</line> <line>__start_table|名称|初始数量|现有数量<br/></line>  <group n="1"> <line>|<f n="Transportation_Class"><S10.G1.D1/></f>|<S10.G1.D2/>|<S10.G1.D3/><br/></line> </group><line>__stop_table</line> </sub> <sub n="11"> <line><br/>运输工具的损毁将导致此次运输任务难以完成。</line> </sub></main> </msg> </msgs>